ssr_url_parser/__init__.py
ssr_url_parser/exceptions.py
ssr_url_parser/utils.py
ssr_url_parser/scripts/__init__.py
ssr_url_parser/scripts/parse_ssr_url.py
ssr_url_parser-0.1.dist-info/METADATA
ssr_url_parser-0.1.dist-info/RECORD
ssr_url_parser-0.1.dist-info/WHEEL
ssr_url_parser-0.1.dist-info/entry_points.txt
ssr_url_parser-0.1.dist-info/top_level.txt
