Metadata-Version: 2.1
Name: ssr-url-parser
Version: 0.1
Summary: A tiny CLI tool for parsing SSR url to plain text.
Home-page: https://github.com/tyong920/ssr_url_parser
Author: tyong920
Author-email: tyong920@gmail.com
License: https://www.gnu.org/licenses/lgpl-3.0.en.html
Platform: UNKNOWN
Classifier: Development Status :: 6 - Mature
Classifier: Environment :: Console
Classifier: License :: OSI Approved :: GNU General Public License v3 or later (GPLv3+)
Classifier: Operating System :: OS Independent
Classifier: Programming Language :: Python :: 3 :: Only
Classifier: Programming Language :: Python :: Implementation
Classifier: Topic :: Software Development :: Libraries :: Python Modules
Classifier: Topic :: Utilities
Requires-Dist: Click
